BotnoiDevPlatform/__init__.py
BotnoiDevPlatform/channels/MOD_BotChannel.py
BotnoiDevPlatform/channels/MOD_FacebookPage.py
BotnoiDevPlatform/channels/__init__.py
BotnoiDevPlatform/cores/MOD_BotnoiChatbotServer.py
BotnoiDevPlatform/cores/MOD_BotnoiClient.py
BotnoiDevPlatform/cores/__init__.py
BotnoiDevPlatform/elements/MOD_ApiObject.py
BotnoiDevPlatform/elements/MOD_AudioObject.py
BotnoiDevPlatform/elements/MOD_Bot.py
BotnoiDevPlatform/elements/MOD_ButtonObject.py
BotnoiDevPlatform/elements/MOD_CarouselObject.py
BotnoiDevPlatform/elements/MOD_CustomPayloadObject.py
BotnoiDevPlatform/elements/MOD_DialogueObject.py
BotnoiDevPlatform/elements/MOD_ImageObject.py
BotnoiDevPlatform/elements/MOD_Intent.py
BotnoiDevPlatform/elements/MOD_IntentKeyword.py
BotnoiDevPlatform/elements/MOD_IntentReaction.py
BotnoiDevPlatform/elements/MOD_Object.py
BotnoiDevPlatform/elements/__init__.py
BotnoiDevPlatform/operators/MOD_BotOpt.py
BotnoiDevPlatform/operators/MOD_IntentOpt.py
BotnoiDevPlatform/operators/__init__.py
BotnoiDevPlatform/utils/MOD_Action.py
BotnoiDevPlatform/utils/MOD_ObjectNamer.py
BotnoiDevPlatform/utils/MOD_ObjectType.py
BotnoiDevPlatform/utils/__init__.py
BotnoiDevPlatform-0.0.8.dist-info/METADATA
BotnoiDevPlatform-0.0.8.dist-info/WHEEL
BotnoiDevPlatform-0.0.8.dist-info/top_level.txt
BotnoiDevPlatform-0.0.8.dist-info/RECORD
